lazy_injector/__init__.py
lazy_injector/dependency.py
lazy_injector/exceptions.py
lazy_injector/provider.py
lazy_injector/singleton.py
lazy_injector-0.0.2.dist-info/METADATA
lazy_injector-0.0.2.dist-info/WHEEL
lazy_injector-0.0.2.dist-info/top_level.txt
lazy_injector-0.0.2.dist-info/RECORD
