Metadata-Version: 2.1
Name: lazy-injector
Version: 0.0.2
Summary: Simple dependency injection package
Home-page: https://github.com/pettermoe95/python-lazy-injector/tree/main
Author: Petter Elenius Moe
Author-email: pettermoe9530@gmail.com
